tests/__init__.py
tests/test_parse.py
whatsapp_converter/__init__.py
whatsapp_converter/__main__.py
whatsapp_converter/colors.py
whatsapp_converter/version.py
whatsapp_converter/whatsapp_converter.py
whatsapp_converter-0.6.4.dist-info/LICENSE
whatsapp_converter-0.6.4.dist-info/METADATA
whatsapp_converter-0.6.4.dist-info/WHEEL
whatsapp_converter-0.6.4.dist-info/entry_points.txt
whatsapp_converter-0.6.4.dist-info/top_level.txt
whatsapp_converter-0.6.4.dist-info/RECORD
