Metadata-Version: 2.1
Name: whatsapp-converter
Version: 0.6.4
Summary: Use whatsapp-converter to convert your exported WhatsApp chat to a CSV or XLS (Excel spreadsheet) file.
Home-page: https://github.com/sandsturm/whatsapp-converter
Author: Martin Sand
Author-email: marti.sand.dev@gmail.com
License: LICENSE.txt
Project-URL: Source, https://github.com/sandsturm/whatsapp-converter/
Project-URL: Bug Reports, https://github.com/sandsturm/whatsapp-converter/issues
Keywords: whatsapp text converter conversion analysis
Classifier: Development Status :: 5 - Production/Stable
Classifier: Environment :: Console
Classifier: Programming Language :: Python :: 3
Classifier: License :: OSI Approved :: MIT License
Classifier: Operating System :: OS Independent
Classifier: Intended Audience :: End Users/Desktop
Classifier: Topic :: Text Processing
Requires-Python: >=3
License-File: LICENSE
Requires-Dist: tqdm
Requires-Dist: pyexcel
Requires-Dist: pyexcel-xlsxw
Requires-Dist: pyexcel-ods3
